setup.py
src/digimat/__init__.py
src/digimat.wirelesstag.egg-info/PKG-INFO
src/digimat.wirelesstag.egg-info/SOURCES.txt
src/digimat.wirelesstag.egg-info/dependency_links.txt
src/digimat.wirelesstag.egg-info/namespace_packages.txt
src/digimat.wirelesstag.egg-info/not-zip-safe
src/digimat.wirelesstag.egg-info/requires.txt
src/digimat.wirelesstag.egg-info/top_level.txt
src/digimat/wirelesstag/__init__.py
src/digimat/wirelesstag/wirelesstag.py