Metadata-Version: 1.0
Name: digimat.wirelesstag
Version: 0.1.2
Summary: Digimat Wirelesstag
Home-page: UNKNOWN
Author: Frederic Hess
Author-email: fhess@splust.ch
License: PSF
Platform: UNKNOWN
